pygridagg/__init__.py
pygridagg/aggregate.py
pygridagg/grid_layouts.py
pygridagg/utils.py
pygridagg/examples/__init__.py
pygridagg/examples/example1.py
pygridagg/examples/example1b.py
pygridagg/examples/example2.py
pygridagg/examples/example3.py
pygridagg/examples/data/quakes_jpn.npy
pygridagg/tests/__init__.py
pygridagg/tests/test_agg.py
pygridagg/tests/test_data_formatting.py
pygridagg/tests/test_grid_construction.py
PyGridAgg-0.1.1.dist-info/LICENSE.txt
PyGridAgg-0.1.1.dist-info/METADATA
PyGridAgg-0.1.1.dist-info/WHEEL
PyGridAgg-0.1.1.dist-info/top_level.txt
PyGridAgg-0.1.1.dist-info/RECORD
