Metadata-Version: 2.1
Name: PyGridAgg
Version: 0.1.1
Summary: Quickly and easily aggregate point data on customisable 2D grids.
Home-page: https://github.com/lungoruscello/PyGridAgg
Author: S. Langenbach
License: MIT
Platform: UNKNOWN
Classifier: Programming Language :: Python :: 3
Classifier: License :: OSI Approved :: MIT License
Classifier: Operating System :: OS Independent
Requires-Python: >=3.6
License-File: LICENSE.txt
Requires-Dist: numpy
Requires-Dist: matplotlib
Provides-Extra: dev
Requires-Dist: pytest (>=7.0) ; extra == 'dev'
Requires-Dist: twine (>=4.0.2) ; extra == 'dev'
